README.md
setup.cfg
setup.py
pna_finder/__init__.py
pna_finder/align_tools.py
pna_finder/pna_finder.py
pna_finder/pna_pipeline.py
pna_finder/pna_solubility.py
pna_finder/pna_tools.py
pna_finder/start_info.py
pna_finder/string_genes.py
pna_finder.egg-info/PKG-INFO
pna_finder.egg-info/SOURCES.txt
pna_finder.egg-info/dependency_links.txt
pna_finder.egg-info/requires.txt
pna_finder.egg-info/top_level.txt