Metadata-Version: 2.1
Name: pna-finder
Version: 0.2
Summary: A toolbox for identifying PNA antisense sequences
Home-page: https://github.com/taunins/pna_finder
Author: Thomas Aunins
Author-email: 
License: GNU LGPLv3
Platform: UNKNOWN
Classifier: Programming Language :: Python :: 3
Classifier: Operating System :: Microsoft
Classifier: Topic :: Scientific/Engineering :: Bio-Informatics
Classifier: License :: OSI Approved :: GNU General Public License v3 (GPLv3)
Requires-Python: >=2.7
